[
    {
        "SirketIsmi":"Halk Gayrimenkul Yatırım Ortaklığı A.Ş.",
        "Sektor":"Gayrimenkul",
        "HisseKodu":"HLGYO",
        "Hacim":21968110,
        "Temettü Verimliliği":0.14,
        "PD_DD":0.3180746194,
        "FD_FAVOK":12.2439796624,
        "FD_Satislar":2.4514985894,
        "FK":3.0343931509,
        "FAVOK":608000000.0,
        "ROA":9.69,
        "PD":13358400000.0
    },
    {
        "SirketIsmi":"Aksa Enerji Üretim A.Ş.",
        "Sektor":"Enerji",
        "HisseKodu":"AKSEN",
        "Hacim":22843130,
        "Temettü Verimliliği":3.52,
        "PD_DD":1.0118688408,
        "FD_FAVOK":10.0114739537,
        "FD_Satislar":2.4560259756,
        "FK":37.4588969263,
        "FAVOK":2552110000.0,
        "ROA":1.53,
        "PD":49519537969.6800003052
    },
    {
        "SirketIsmi":"Konfrut Gıda Pazarlama ve Sanayi A.Ş.",
        "Sektor":"Gıda",
        "HisseKodu":"KNFRT",
        "Hacim":4670818,
        "Temettü Verimliliği":null,
        "PD_DD":3.8027207776,
        "FD_FAVOK":179.8525618682,
        "FD_Satislar":1.2910802351,
        "FK":0.0,
        "FAVOK":-23440000.0,
        "ROA":-9.31,
        "PD":5016000000.0
    },
    {
        "SirketIsmi":"Lokman Hekim Engürüsağlık A.Ş.",
        "Sektor":"Sağlık",
        "HisseKodu":"LKMNH",
        "Hacim":1585514,
        "Temettü Verimliliği":2.28,
        "PD_DD":1.6424153595,
        "FD_FAVOK":7.4458261905,
        "FD_Satislar":1.6865510547,
        "FK":21.7944777911,
        "FAVOK":180170000.0,
        "ROA":2.25,
        "PD":3630959999.9999990463
    },
    {
        "SirketIsmi":"Logo Yazılım Sanayi ve Ticaret A.Ş.",
        "Sektor":"Teknoloji",
        "HisseKodu":"LOGO",
        "Hacim":346039,
        "Temettü Verimliliği":2.81,
        "PD_DD":5.22338004,
        "FD_FAVOK":9.8748729293,
        "FD_Satislar":3.6184794374,
        "FK":13.9871705359,
        "FAVOK":548440000.0,
        "ROA":17.5,
        "PD":16026499999.9999980927
    },
    {
        "SirketIsmi":"Netaş Telekomünikasyon A.Ş.",
        "Sektor":"Teknoloji",
        "HisseKodu":"NETAS",
        "Hacim":1322255,
        "Temettü Verimliliği":null,
        "PD_DD":-61.8239064957,
        "FD_FAVOK":32.2217530843,
        "FD_Satislar":0.6909513286,
        "FK":0.0,
        "FAVOK":102380000.0,
        "ROA":-1.53,
        "PD":5091886800.0
    },
    {
        "SirketIsmi":"Nurol Gayrimenkul Yatırım Ortaklığı A.Ş.",
        "Sektor":"Gayrimenkul",
        "HisseKodu":"NUGYO",
        "Hacim":2369185,
        "Temettü Verimliliği":null,
        "PD_DD":0.5765948722,
        "FD_FAVOK":-29.2630316703,
        "FD_Satislar":5.1007492551,
        "FK":0.0,
        "FAVOK":-35700000.0,
        "ROA":-2.82,
        "PD":3454084400.0
    },
    {
        "SirketIsmi":"Otokar Otomotiv ve Savunma Sanayi A.Ş.",
        "Sektor":"Otomotiv",
        "HisseKodu":"OTKAR",
        "Hacim":496261,
        "Temettü Verimliliği":1.32,
        "PD_DD":6.3732237745,
        "FD_FAVOK":55.3496916319,
        "FD_Satislar":2.0846038185,
        "FK":0.0,
        "FAVOK":1467230000.0,
        "ROA":-0.17,
        "PD":56940000000.0
    },
    {
        "SirketIsmi":"Polisan Holding A.Ş.",
        "Sektor":"Holding",
        "HisseKodu":"POLHO",
        "Hacim":14472070,
        "Temettü Verimliliği":0.55,
        "PD_DD":4.6551055497,
        "FD_FAVOK":108.3262441287,
        "FD_Satislar":14.4320733486,
        "FK":0.0,
        "FAVOK":266410000.0,
        "ROA":-2.22,
        "PD":81459669748.5999908447
    },
    {
        "SirketIsmi":"Selçuk Ecza Deposu Ticaret ve Sanayi A.Ş.",
        "Sektor":"Sağlık",
        "HisseKodu":"SELEC",
        "Hacim":1614206,
        "Temettü Verimliliği":0.38,
        "PD_DD":1.8060203708,
        "FD_FAVOK":10.5825680401,
        "FD_Satislar":0.3165076002,
        "FK":40.4091675571,
        "FAVOK":651680000.0,
        "ROA":-0.53,
        "PD":48406950000.0
    },
    {
        "SirketIsmi":"Türkiye Şişe ve Cam Fabrikaları A.Ş.",
        "Sektor":"Tüketim",
        "HisseKodu":"SISE",
        "Hacim":39990280,
        "Temettü Verimliliği":1.54,
        "PD_DD":0.498369671,
        "FD_FAVOK":18.9105571977,
        "FD_Satislar":1.2946405033,
        "FK":43.3497415589,
        "FAVOK":5543070000.0,
        "ROA":0.97,
        "PD":108192718480.0
    },
    {
        "SirketIsmi":"Şok Marketler Ticaret A.Ş.",
        "Sektor":"Perakende",
        "HisseKodu":"SOKM",
        "Hacim":5986282,
        "Temettü Verimliliği":6.54,
        "PD_DD":0.671523155,
        "FD_FAVOK":10.7937683245,
        "FD_Satislar":0.1190173174,
        "FK":0.0,
        "FAVOK":806020000.0,
        "ROA":-0.91,
        "PD":21951730296.0
    },
    {
        "SirketIsmi":"Türkiye Petrol Rafinerileri A.Ş.",
        "Sektor":"Kimya",
        "HisseKodu":"TUPRS",
        "Hacim":16770810,
        "Temettü Verimliliği":9.23,
        "PD_DD":1.1348231948,
        "FD_FAVOK":6.8312357243,
        "FD_Satislar":0.4517341288,
        "FK":17.3340345864,
        "FAVOK":14069640000.0,
        "ROA":1.86,
        "PD":347979357600.0
    },
    {
        "SirketIsmi":"Tat Gıda Sanayi A.Ş.",
        "Sektor":"Gıda",
        "HisseKodu":"TATGD",
        "Hacim":1345239,
        "Temettü Verimliliği":null,
        "PD_DD":0.8647027778,
        "FD_FAVOK":29.575627822,
        "FD_Satislar":1.0210478012,
        "FK":58.4026755853,
        "FAVOK":4520000.0,
        "ROA":-1.24,
        "PD":3143232000.0
    },
    {
        "SirketIsmi":"TAV Havalimanları Holding A.Ş.",
        "Sektor":"Ulaşım",
        "HisseKodu":"TAVHL",
        "Hacim":1881462,
        "Temettü Verimliliği":null,
        "PD_DD":1.221736338,
        "FD_FAVOK":7.7444080799,
        "FD_Satislar":2.1968910348,
        "FK":47.2262110387,
        "FAVOK":6351060000.0,
        "ROA":-0.96,
        "PD":86061268900.0
    },
    {
        "SirketIsmi":"Türk Hava Yolları A.O.",
        "Sektor":"Ulaşım",
        "HisseKodu":"THYAO",
        "Hacim":32264090,
        "Temettü Verimliliği":2.06,
        "PD_DD":0.575708741,
        "FD_FAVOK":5.3748084713,
        "FD_Satislar":0.9330335834,
        "FK":4.2841240786,
        "FAVOK":46071000000.0,
        "ROA":1.73,
        "PD":432975000000.0
    },
    {
        "SirketIsmi":"Tümosan Motor ve Traktör Sanayi A.Ş.",
        "Sektor":"Otomotiv",
        "HisseKodu":"TMSN",
        "Hacim":800332,
        "Temettü Verimliliği":null,
        "PD_DD":0.7755007908,
        "FD_FAVOK":-14.0973728783,
        "FD_Satislar":3.1311259232,
        "FK":2.1601994531,
        "FAVOK":-779860000.0,
        "ROA":37.45,
        "PD":12615500000.0
    },
    {
        "SirketIsmi":"Kartonsan Karton Sanayi ve Ticaret A.Ş.",
        "Sektor":"Kağıt",
        "HisseKodu":"KARTN",
        "Hacim":197097,
        "Temettü Verimliliği":null,
        "PD_DD":2.3602064408,
        "FD_FAVOK":-10.7389094841,
        "FD_Satislar":2.1234900108,
        "FK":0.0,
        "FAVOK":-251560000.0,
        "ROA":-14.73,
        "PD":6281250000.0
    },
    {
        "SirketIsmi":"Adel Kalemcilik Ticaret ve Sanayi A.Ş.",
        "Sektor":"Kağıt",
        "HisseKodu":"ADEL",
        "Hacim":1144696,
        "Temettü Verimliliği":1.62,
        "PD_DD":5.7925928826,
        "FD_FAVOK":403.9698313149,
        "FD_Satislar":4.813254021,
        "FK":0.0,
        "FAVOK":127680000.0,
        "ROA":-5.04,
        "PD":7915792500.0
    },
    {
        "SirketIsmi":"İzmir Demir Çelik Sanayi A.Ş.",
        "Sektor":"Sanayi",
        "HisseKodu":"IZMDC",
        "Hacim":4392681,
        "Temettü Verimliliği":null,
        "PD_DD":0.5736025253,
        "FD_FAVOK":43.7244490501,
        "FD_Satislar":0.6435953401,
        "FK":1303.8309114927,
        "FAVOK":128010000.0,
        "ROA":-1.45,
        "PD":9870000000.0
    },
    {
        "SirketIsmi":"Tofaş Türk Otomobil Fabrikası A.Ş.",
        "Sektor":"Otomotiv",
        "HisseKodu":"TOASO",
        "Hacim":7167757,
        "Temettü Verimliliği":5.54,
        "PD_DD":2.889260626,
        "FD_FAVOK":72.605882648,
        "FD_Satislar":1.1884451961,
        "FK":142.6122991917,
        "FAVOK":2519310000.0,
        "ROA":1.4,
        "PD":139375000000.0
    },
    {
        "SirketIsmi":"Alkim Kağıt Sanayi ve Ticaret A.Ş.",
        "Sektor":"Kimya",
        "HisseKodu":"ALKA",
        "Hacim":8005062,
        "Temettü Verimliliği":null,
        "PD_DD":4.5914229739,
        "FD_FAVOK":89.0166682913,
        "FD_Satislar":3.8211084797,
        "FK":0.0,
        "FAVOK":16560000.0,
        "ROA":-0.56,
        "PD":8893500000.0
    },
    {
        "SirketIsmi":"Arçelik A.Ş.",
        "Sektor":"Tüketim",
        "HisseKodu":"ARCLK",
        "Hacim":3303176,
        "Temettü Verimliliği":null,
        "PD_DD":1.1411948876,
        "FD_FAVOK":10.7737809399,
        "FD_Satislar":0.529535111,
        "FK":0.0,
        "FAVOK":7358650000.0,
        "ROA":-0.91,
        "PD":78722312000.0
    },
    {
        "SirketIsmi":"Aselsan Elektronik Sanayi A.Ş.",
        "Sektor":"Teknoloji",
        "HisseKodu":"ASELS",
        "Hacim":32204140,
        "Temettü Verimliliği":0.13,
        "PD_DD":5.6454040283,
        "FD_FAVOK":30.5120232624,
        "FD_Satislar":7.758953055,
        "FK":57.568378714,
        "FAVOK":8086090000.0,
        "ROA":2.69,
        "PD":954088800000.0
    },
    {
        "SirketIsmi":"A.V.O.D. Kurutulmuş Gıda ve Tarım Ürünleri A.Ş.",
        "Sektor":"Gıda",
        "HisseKodu":"AVOD",
        "Hacim":8233046,
        "Temettü Verimliliği":null,
        "PD_DD":1.0762469311,
        "FD_FAVOK":14.0593473875,
        "FD_Satislar":1.4373764102,
        "FK":0.0,
        "FAVOK":62020000.0,
        "ROA":-5.83,
        "PD":1198800000.0
    },
    {
        "SirketIsmi":"Aygaz A.Ş.",
        "Sektor":"Enerji",
        "HisseKodu":"AYGAZ",
        "Hacim":466625,
        "Temettü Verimliliği":9.53,
        "PD_DD":0.6968535115,
        "FD_FAVOK":15.0170225073,
        "FD_Satislar":0.5090711758,
        "FK":14.7557040892,
        "FAVOK":627880000.0,
        "ROA":1.57,
        "PD":40685165100.0
    },
    {
        "SirketIsmi":"Bağfaş Bandırma Gübre Fabrikaları A.Ş.",
        "Sektor":"Kimya",
        "HisseKodu":"BAGFS",
        "Hacim":3224433,
        "Temettü Verimliliği":null,
        "PD_DD":0.7098748268,
        "FD_FAVOK":6.7194096245,
        "FD_Satislar":2.6673722372,
        "FK":0.0,
        "FAVOK":350840000.0,
        "ROA":1.93,
        "PD":4695300000.0
    },
    {
        "SirketIsmi":"Bim Birleşik Mağazalar A.Ş.",
        "Sektor":"Perakende",
        "HisseKodu":"BIMAS",
        "Hacim":3316091,
        "Temettü Verimliliği":2.23,
        "PD_DD":2.5089644592,
        "FD_FAVOK":14.2766997871,
        "FD_Satislar":0.7039161943,
        "FK":27.5145883124,
        "FAVOK":9794770000.0,
        "ROA":2.24,
        "PD":340200000000.0
    },
    {
        "SirketIsmi":"Borusan Birleşik Boru Fabrikaları A.Ş.",
        "Sektor":"Sanayi",
        "HisseKodu":"BRSAN",
        "Hacim":602806,
        "Temettü Verimliliği":null,
        "PD_DD":1.6765507405,
        "FD_FAVOK":32.8006931034,
        "FD_Satislar":1.2196592632,
        "FK":0.0,
        "FAVOK":1550900000.0,
        "ROA":0.9,
        "PD":57736647000.0
    },
    {
        "SirketIsmi":"Çelebi Hava Servisi A.Ş.",
        "Sektor":"Ulaşım",
        "HisseKodu":"CLEBI",
        "Hacim":126411,
        "Temettü Verimliliği":8.62,
        "PD_DD":7.2255368422,
        "FD_FAVOK":7.8505002901,
        "FD_Satislar":2.0881438533,
        "FK":11.6180245502,
        "FAVOK":1394200000.0,
        "ROA":4.42,
        "PD":38199600000.0
    },
    {
        "SirketIsmi":"CarrefourSA Ticaret Merkezi A.Ş.",
        "Sektor":"Perakende",
        "HisseKodu":"CRFSA",
        "Hacim":1398586,
        "Temettü Verimliliği":null,
        "PD_DD":8.3860266501,
        "FD_FAVOK":10.9475087021,
        "FD_Satislar":0.418798441,
        "FK":0.0,
        "FAVOK":517280000.0,
        "ROA":-11.41,
        "PD":14055140000.0
    },
    {
        "SirketIsmi":"Eczacıbaşı İlaç Sınai ve Finansal Yatırımlar A.Ş.",
        "Sektor":"Sağlık",
        "HisseKodu":"ECILC",
        "Hacim":4604052,
        "Temettü Verimliliği":3.41,
        "PD_DD":1.1713652779,
        "FD_FAVOK":-135.9858051884,
        "FD_Satislar":7.8033066925,
        "FK":22.5013715032,
        "FAVOK":-275250000.0,
        "ROA":3.28,
        "PD":62016030000.0
    },
    {
        "SirketIsmi":"Emlak Konut Gayrimenkul Yatırım Ortaklığı A.Ş.",
        "Sektor":"Gayrimenkul",
        "HisseKodu":"EKGYO",
        "Hacim":154252200,
        "Temettü Verimliliği":2.22,
        "PD_DD":0.6192789091,
        "FD_FAVOK":6.4442410937,
        "FD_Satislar":1.2740414846,
        "FK":3.6719446763,
        "FAVOK":6799340000.0,
        "ROA":4.39,
        "PD":74480000000.0
    },
    {
        "SirketIsmi":"Enerjisa Enerji A.Ş.",
        "Sektor":"Enerjisa",
        "HisseKodu":"ENJSA",
        "Hacim":1953613,
        "Temettü Verimliliği":4.17,
        "PD_DD":1.1377845214,
        "FD_FAVOK":4.4897032159,
        "FD_Satislar":0.7932488509,
        "FK":0.0,
        "FAVOK":9894850000.0,
        "ROA":-0.15,
        "PD":94544573450.0
    },
    {
        "SirketIsmi":"Erbosan Erciyas Boru Sanayii A.Ş.",
        "Sektor":"Sanayi",
        "HisseKodu":"ERBOS",
        "Hacim":57051,
        "Temettü Verimliliği":1.56,
        "PD_DD":1.2783817668,
        "FD_FAVOK":59.9183673469,
        "FD_Satislar":1.0253390929,
        "FK":0.0,
        "FAVOK":48050000.0,
        "ROA":-4.42,
        "PD":3672000000.0
    },
    {
        "SirketIsmi":"Global Yatırım Holding A.Ş.",
        "Sektor":"Holding",
        "HisseKodu":"GLYHO",
        "Hacim":56786900,
        "Temettü Verimliliği":0.67,
        "PD_DD":1.7991912889,
        "FD_FAVOK":9.1201063524,
        "FD_Satislar":2.9864225117,
        "FK":5.1546932354,
        "FAVOK":2140070000.0,
        "ROA":1.84,
        "PD":19168500000.0
    },
    {
        "SirketIsmi":"İhlas Holding A.Ş.",
        "Sektor":"Holding",
        "HisseKodu":"IHLAS",
        "Hacim":60549470,
        "Temettü Verimliliği":null,
        "PD_DD":1.1672017894,
        "FD_FAVOK":-9.8556899761,
        "FD_Satislar":0.5997403144,
        "FK":0.0,
        "FAVOK":-508740000.0,
        "ROA":-3.61,
        "PD":5280000000.0
    },
    {
        "SirketIsmi":"Yataş Yatak ve Yorgan Sanayi A.Ş.",
        "Sektor":"Tüketim",
        "HisseKodu":"YATAS",
        "Hacim":1418860,
        "Temettü Verimliliği":null,
        "PD_DD":0.5170260492,
        "FD_FAVOK":6.1352410245,
        "FD_Satislar":0.6259541514,
        "FK":0.0,
        "FAVOK":524140000.0,
        "ROA":-0.55,
        "PD":4868465290.0
    }
]